{
  "name": "nze50_ts1",
  "data": [
    {
      "seriesName": "PRC_ELC_GAS",
      "seriesValues": [
        [
          2021,
          13.54996307238564
        ]
      ]
    },
    {
      "seriesName": "PRC_ELC_SPV",
      "seriesValues": [
        [
          2021,
          597.8118546235843
        ],
        [
          2024,
          140.62361633347027
        ],
        [
          2025,
          161.69739851767005
        ],
        [
          2026,
          168.18148524907488
        ],
        [
          2027,
          199.82530317220187
        ],
        [
          2028,
          251.9857391626869
        ],
        [
          2029,
          286.2043822401716
        ],
        [
          2030,
          358.2482975569116
        ],
        [
          2031,
          218.53563964977602
        ],
        [
          2032,
          77.38245257264211
        ],
        [
          2033,
          71.51663091950634
        ],
        [
          2034,
          56.934448173997886
        ],
        [
          2035,
          35.161133667226046
        ],
        [
          2036,
          57.1465114139107
        ],
        [
          2037,
          69.31494747557564
        ],
        [
          2038,
          53.41991555694174
        ],
        [
          2039,
          91.93375833000626
        ],
        [
          2040,
          92.62603169229777
        ],
        [
          2041,
          68.48819641620209
        ],
        [
          2042,
          70.22094158376342
        ],
        [
          2043,
          62.75605050176878
        ],
        [
          2044,
          51.01856193799663
        ],
        [
          2045,
          53.76842198665571
        ],
        [
          2046,
          77.31993120456332
        ],
        [
          2047,
          40.105722030786175
        ],
        [
          2048,
          46.72989356693991
        ],
        [
          2049,
          85.39239308977407
        ],
        [
          2050,
          117.63372871900583
        ]
      ]
    },
    {
      "seriesName": "PRC_ELC_WNO",
      "seriesValues": [
        [
          2021,
          413.3458124046555
        ],
        [
          2024,
          14.8954915033365
        ],
        [
          2025,
          19.1439955687035
        ],
        [
          2026,
          21.2498350812609
        ],
        [
          2027,
          5.43837906946242
        ],
        [
          2030,
          0.491700288963941
        ]
      ]
    }
  ]
}